topf/HomologyGeneratorsMultiD.jl
topf/JuliaManifest.toml
topf/JuliaProject.toml
topf/__init__.py
topf/topfmain.py
topf-1.0.3.dist-info/METADATA
topf-1.0.3.dist-info/WHEEL
topf-1.0.3.dist-info/licenses/LICENSE
topf-1.0.3.dist-info/RECORD
