Metadata-Version: 2.3
Name: topf
Version: 1.0.3
Summary: TOpological Point Features: Node-Level Topological Representation Learning on Point Clouds
Project-URL: Homepage, https://github.com/vincent-grande/topf
Author-email: "Vincent P. Grande" <grande@cs.rwth-aachen.de>
License-File: LICENSE
Classifier: License :: OSI Approved :: MIT License
Classifier: Operating System :: OS Independent
Classifier: Programming Language :: Python :: 3
Requires-Python: >=3.9
Requires-Dist: gudhi>=3.8.0
Requires-Dist: matplotlib>=3.9.0
Requires-Dist: nbformat>=5.10.0
Requires-Dist: numpy>=1.22.0
Requires-Dist: pandas>=2.2.2
Requires-Dist: plotly>=5.22.0
Requires-Dist: scikit-learn>=1.5.0
Requires-Dist: scipy>=1.13.0
